dummyextension/__init__.py
dummyextension/extension.cpython-311-powerpc64le-linux-gnu.so
dummyextension/tests/__init__.py
dummyextension/tests/test_extension.py
simple_manylinux_demo-5.0.dist-info/LICENSE
simple_manylinux_demo-5.0.dist-info/METADATA
simple_manylinux_demo-5.0.dist-info/WHEEL
simple_manylinux_demo-5.0.dist-info/top_level.txt
simple_manylinux_demo-5.0.dist-info/RECORD
