Metadata-Version: 2.4
Name: simple-manylinux-demo
Version: 5.0
Summary: This is a simple package with a compiled C extension.
Home-page: https://github.com/frenzymadness/simple-manylinux-demo
Author: Lumír Balhar
Author-email: frenzy.madness@gmail.com
License: CC0 1.0
License-File: LICENSE
Dynamic: author
Dynamic: author-email
Dynamic: description
Dynamic: home-page
Dynamic: license
Dynamic: license-file
Dynamic: summary
